LICENSE
MANIFEST.in
README.rst
setup.py
secapp/__init__.py
secapp/admin.py
secapp/apps.py
secapp/controller.py
secapp/iptables.py
secapp/models.py
secapp/serializers.py
secapp/tests.py
secapp/urls.py
secapp/views.py
secapp/kernel/__init__.py
secapp/kernel/source.py
secapp/migrations/0001_initial.py
secapp/migrations/0002_auto_20151216_1325.py
secapp/migrations/0003_auto_20160115_1801.py
secapp/migrations/0004_auto_20160116_1407.py
secapp/migrations/0005_visualizations.py
secapp/migrations/0006_visualizations_id_source.py
secapp/migrations/0007_auto_20160209_2153.py
secapp/migrations/0008_auto_20160209_2213.py
secapp/migrations/0009_historic.py
secapp/migrations/__init__.py
secapp/static/gulpfile.js
secapp/static/admin/css/base.css
secapp/static/admin/css/changelists.css
secapp/static/admin/css/dashboard.css
secapp/static/admin/css/fonts.css
secapp/static/admin/css/forms.css
secapp/static/admin/css/login.css
secapp/static/admin/css/rtl.css
secapp/static/admin/css/widgets.css
secapp/static/admin/fonts/LICENSE.txt
secapp/static/admin/fonts/README.txt
secapp/static/admin/fonts/Roboto-Bold-webfont.woff
secapp/static/admin/fonts/Roboto-Light-webfont.woff
secapp/static/admin/fonts/Roboto-Regular-webfont.woff
secapp/static/admin/img/LICENSE
secapp/static/admin/img/README.txt
secapp/static/admin/img/calendar-icons.svg
secapp/static/admin/img/icon-addlink.svg
secapp/static/admin/img/icon-alert.svg
secapp/static/admin/img/icon-calendar.svg
secapp/static/admin/img/icon-changelink.svg
secapp/static/admin/img/icon-clock.svg
secapp/static/admin/img/icon-deletelink.svg
secapp/static/admin/img/icon-no.svg
secapp/static/admin/img/icon-unknown-alt.svg
secapp/static/admin/img/icon-unknown.svg
secapp/static/admin/img/icon-yes.svg
secapp/static/admin/img/inline-delete.svg
secapp/static/admin/img/search.svg
secapp/static/admin/img/selector-icons.svg
secapp/static/admin/img/sorting-icons.svg
secapp/static/admin/img/tooltag-add.svg
secapp/static/admin/img/tooltag-arrowright.svg
security_sensor.egg-info/PKG-INFO
security_sensor.egg-info/SOURCES.txt
security_sensor.egg-info/dependency_links.txt
security_sensor.egg-info/top_level.txt